streamlit_prophet/__init__.py
streamlit_prophet/app/__init__.py
streamlit_prophet/app/dashboard.py
streamlit_prophet/cli/__init__.py
streamlit_prophet/cli/__main__.py
streamlit_prophet/cli/deploy.py
streamlit_prophet/config/config_instructions.toml
streamlit_prophet/config/config_readme.toml
streamlit_prophet/config/config_streamlit.toml
streamlit_prophet/lib/__init__.py
streamlit_prophet/lib/dataprep/__init__.py
streamlit_prophet/lib/dataprep/clean.py
streamlit_prophet/lib/dataprep/format.py
streamlit_prophet/lib/dataprep/split.py
streamlit_prophet/lib/evaluation/__init__.py
streamlit_prophet/lib/evaluation/metrics.py
streamlit_prophet/lib/evaluation/preparation.py
streamlit_prophet/lib/exposition/__init__.py
streamlit_prophet/lib/exposition/expanders.py
streamlit_prophet/lib/exposition/export.py
streamlit_prophet/lib/exposition/preparation.py
streamlit_prophet/lib/exposition/visualize.py
streamlit_prophet/lib/inputs/__init__.py
streamlit_prophet/lib/inputs/dataprep.py
streamlit_prophet/lib/inputs/dataset.py
streamlit_prophet/lib/inputs/dates.py
streamlit_prophet/lib/inputs/eval.py
streamlit_prophet/lib/inputs/params.py
streamlit_prophet/lib/models/__init__.py
streamlit_prophet/lib/models/preparation.py
streamlit_prophet/lib/models/prophet.py
streamlit_prophet/lib/utils/__init__.py
streamlit_prophet/lib/utils/holidays.py
streamlit_prophet/lib/utils/load.py
streamlit_prophet/lib/utils/logging.py
streamlit_prophet/lib/utils/mapping.py
streamlit_prophet/lib/utils/misc.py
streamlit_prophet/py.typed
streamlit_prophet/references/input_format.png
streamlit_prophet/references/logo.png
streamlit_prophet/report/config/.gitignore
streamlit_prophet/report/data/.gitignore
streamlit_prophet/report/plots/.gitignore
streamlit_prophet-1.0.0.dist-info/entry_points.txt
streamlit_prophet-1.0.0.dist-info/LICENSE
streamlit_prophet-1.0.0.dist-info/WHEEL
streamlit_prophet-1.0.0.dist-info/METADATA
streamlit_prophet-1.0.0.dist-info/RECORD
