Metadata-Version: 2.1
Name: streamlit-prophet
Version: 1.0.0
Summary: Deploy a Streamlit app to train, evaluate and optimize a Prophet forecasting model visually.
Home-page: https://github.com/artefactory-global/streamlit_prophet
License: MIT
Keywords: streamlit,prophet,forecasting,time-series,data-science
Author: Maxime Lutel
Author-email: maxime.lutel@artefact.com
Requires-Python: >=3.7,<3.10
Classifier: Development Status :: 3 - Alpha
Classifier: Intended Audience :: Developers
Classifier: License :: OSI Approved :: MIT License
Classifier: Programming Language :: Python :: 3
Classifier: Programming Language :: Python :: 3.7
Classifier: Programming Language :: Python :: 3.8
Classifier: Programming Language :: Python :: 3.9
Classifier: Topic :: Software Development :: Libraries :: Python Modules
Requires-Dist: fbprophet (==0.7.1)
Requires-Dist: holidays (>=0.11.1,<0.12.0)
Requires-Dist: importlib_metadata (>=1.6.0,<2.0.0); python_version < "3.8"
Requires-Dist: numpy (>=1.20.2,<2.0.0)
Requires-Dist: pandas (>=1.1.5,<2.0.0)
Requires-Dist: plotly (>=4.11.0,<5.0.0)
Requires-Dist: pystan (==2.19.1.1)
Requires-Dist: rich (>=10.1.0,<11.0.0)
Requires-Dist: scipy (>=1.6.3,<2.0.0)
Requires-Dist: streamlit (==0.80.0)
Requires-Dist: typer[all] (>=0.3.2,<0.4.0)
Requires-Dist: vacances-scolaires-france (>=0.8.0,<0.9.0)
Project-URL: Repository, https://github.com/artefactory-global/streamlit_prophet
